squirrely/__init__.py
squirrely/core.py
squirrely/main.py
squirrely-0.1.1.dist-info/licenses/LICENSE
squirrely-0.1.1.dist-info/METADATA
squirrely-0.1.1.dist-info/WHEEL
squirrely-0.1.1.dist-info/entry_points.txt
squirrely-0.1.1.dist-info/top_level.txt
squirrely-0.1.1.dist-info/RECORD
