Metadata-Version: 2.4
Name: squirrely
Version: 0.1.1
Summary: ディレクトリ構成をMarkdownで生成するツール
Home-page: 
Author: K the Owl
Requires-Python: >=3.8
License-File: LICENSE
Dynamic: author
Dynamic: description
Dynamic: description-content-type
Dynamic: license-file
Dynamic: requires-python
Dynamic: summary
